shell2launch.py
shell2launch-0.0.1.dist-info/LICENSE
shell2launch-0.0.1.dist-info/METADATA
shell2launch-0.0.1.dist-info/WHEEL
shell2launch-0.0.1.dist-info/entry_points.txt
shell2launch-0.0.1.dist-info/top_level.txt
shell2launch-0.0.1.dist-info/RECORD
