Metadata-Version: 2.2
Name: shell2launch
Version: 0.0.1
Summary: Transform shell code that invokes python scripts to vscode debug configurations.
Author: Jakob Jung
License: MIT License
Project-URL: Homepage, https://github.com/jjaju/shell2launch
Project-URL: Issues, https://github.com/jjaju/shell2launch/issues
Keywords: vscode,debug
Classifier: Programming Language :: Python :: 3
Classifier: Programming Language :: Python :: 3.9
Classifier: Programming Language :: Python :: 3.10
Classifier: Programming Language :: Python :: 3.11
Classifier: Programming Language :: Python :: 3.12
Classifier: Programming Language :: Python :: 3.13
Classifier: Programming Language :: Python :: 3 :: Only
Classifier: Operating System :: OS Independent
Classifier: License :: OSI Approved :: MIT License
Classifier: Intended Audience :: Developers
Requires-Python: >=3.9
License-File: LICENSE
